markdown_css/__init__.py
markdown_css/cli.py
markdown_css-0.0.8.dist-info/LICENSE
markdown_css-0.0.8.dist-info/METADATA
markdown_css-0.0.8.dist-info/WHEEL
markdown_css-0.0.8.dist-info/entry_points.txt
markdown_css-0.0.8.dist-info/top_level.txt
markdown_css-0.0.8.dist-info/RECORD
