Metadata-Version: 2.1
Name: markdown-css
Version: 0.0.8
Summary: Markdown-css is a command tool to convert css style to markdown inline-style
Author-email: sanyuesha <wecatch.me@gmail.com>
Maintainer-email: sanyuesha <wecatch.me@gmail.com>
License: MIT
Project-URL: Homepage, http://github.com/wecatch/markdown-css
Project-URL: Repository, http://github.com/wecatch/markdown-css
Project-URL: Issues, http://github.com/wecatch/markdown-css/issues
Keywords: markdown-css,markdown,css
Classifier: Development Status :: 4 - Beta
Classifier: Intended Audience :: Developers
Classifier: License :: OSI Approved :: MIT License
Classifier: Programming Language :: Python :: 3
Classifier: Programming Language :: Python :: 3.6
Classifier: Programming Language :: Python :: 3.7
Classifier: Programming Language :: Python :: 3.8
Classifier: Programming Language :: Python :: 3.9
Classifier: Programming Language :: Python :: 3.10
Classifier: Programming Language :: Python :: 3.11
Classifier: Programming Language :: Python :: 3.12
Classifier: Topic :: Text Processing :: Markup
Classifier: Topic :: Software Development :: Libraries :: Python Modules
Requires-Python: >=3.6
License-File: LICENSE
Requires-Dist: docopt>=0.6.2
Requires-Dist: cssutils>=2.6.0
Requires-Dist: pyquery>=2.0.0
Requires-Dist: Pygments>=2.15.0
